{
  "valley name": "ROSELEND",
  "date": "07012024",
  "timestep_number": 192,
  "timestep_duration [min]": 15.0,
  "reservoirs": [
    {
      "name": "ROSELR",
      "kind": "lac",
      "water_value": 0.2942,
      "initial_volume": 147182600,
      "supplies": [
        {
          "count": 192,
          "value": 18000
        }
      ],
      "min_volumes": [
        {
          "count": 192,
          "value": 0
        }
      ],
      "max_volumes": [
        {
          "count": 192,
          "value": 176918000
        }
      ]
    },
    {
      "name": "SINK",
      "kind": "lac",
      "water_value": 0.0,
      "initial_volume": 0,
      "supplies": [
        {
          "count": 192,
          "value": 0
        }
      ],
      "min_volumes": [
        {
          "count": 192,
          "value": 0
        }
      ],
      "max_volumes": [
        {
          "count": 192,
          "value": 1000000000
        }
      ]
    }
  ],
  "usines": [
    {
      "name": "BATHIH",
      "type": "turbine",
      "min_duration_high_level": 30,
      "min_duration_low_level": 90,
      "initial_state": {
        "flowrate": 126360,
        "trend": "increase",
        "duration": 120
      },
      "kind": "Turbine",
      "pdf_serie": {
        "pdfs_table": [
          [
            {
              "flowrate": 0,
              "power": 0.0,
              "primary": 0.0,
              "secondary": 0.0
            },
            {
              "flowrate": 20160,
              "power": 58.0,
              "primary": 5.0,
              "secondary": 37.0
            },
            {
              "flowrate": 25560,
              "power": 75.0,
              "primary": 5.0,
              "secondary": 0.0
            },
            {
              "flowrate": 40320,
              "power": 116.0,
              "primary": 10.0,
              "secondary": 74.0
            },
            {
              "flowrate": 60840,
              "power": 174.0,
              "primary": 15.0,
              "secondary": 111.0
            },
            {
              "flowrate": 64800,
              "power": 190.0,
              "primary": 10.0,
              "secondary": 0.0
            },
            {
              "flowrate": 69120,
              "power": 201.0,
              "primary": 15.0,
              "secondary": 0.0
            },
            {
              "flowrate": 82080,
              "power": 232.0,
              "primary": 20.0,
              "secondary": 148.0
            },
            {
              "flowrate": 98280,
              "power": 285.0,
              "primary": 15.0,
              "secondary": 0.0
            },
            {
              "flowrate": 103680,
              "power": 290.0,
              "primary": 25.0,
              "secondary": 185.0
            },
            {
              "flowrate": 126360,
              "power": 348.0,
              "primary": 30.0,
              "secondary": 222.0
            },
            {
              "flowrate": 132120,
              "power": 380.0,
              "primary": 20.0,
              "secondary": 0.0
            },
            {
              "flowrate": 167760,
              "power": 475.0,
              "primary": 25.0,
              "secondary": 0.0
            },
            {
              "flowrate": 204840,
              "power": 570.0,
              "primary": 30.0,
              "secondary": 0.0
            },
            {
              "flowrate": 217800,
              "power": 600.0,
              "primary": 0.0,
              "secondary": 0.0
            }
          ]
        ],
        "pdfs_indices": [
          {
            "count": 192,
            "value": 1
          }
        ]
      },
      "upstream_reservoir": "ROSELR",
      "downstream_reservoir": "SINK"
    }
  ],
  "marginal_costs": {
    "power": [
      90.201,
      90.201,
      81.106,
      81.106,
      70.385,
      70.385,
      92.901,
      92.901,
      77.709,
      77.709,
      76.715,
      76.715,
      71.456,
      71.456,
      68.977,
      68.977,
      68.845,
      68.845,
      68.276,
      68.276,
      51.135,
      51.135,
      82.329,
      82.329,
      36.805,
      36.805,
      79.2,
      79.2,
      56.126,
      56.126,
      69.612,
      69.612,
      69.09,
      69.09,
      70.447,
      70.447,
      74.266,
      74.266,
      78.097,
      78.097,
      72.008,
      72.008,
      83.928,
      83.928,
      66.788,
      66.788,
      90.635,
      90.635,
      65.213,
      65.213,
      90.658,
      90.658,
      80.628,
      80.628,
      65.283,
      65.283,
      70.548,
      70.548,
      74.201,
      74.201,
      91.015,
      91.015,
      61.73,
      61.73,
      81.478,
      81.478,
      82.196,
      82.196,
      82.38,
      82.38,
      102.003,
      102.003,
      78.965,
      78.965,
      110.438,
      110.438,
      95.36,
      95.36,
      92.676,
      92.676,
      95.243,
      95.243,
      91.444,
      91.444,
      90.786,
      90.786,
      84.643,
      84.643,
      72.157,
      72.157,
      103.841,
      103.841,
      88.268,
      88.268,
      79.16,
      79.16,
      90.201,
      90.201,
      81.106,
      81.106,
      70.385,
      70.385,
      92.901,
      92.901,
      77.709,
      77.709,
      76.715,
      76.715,
      71.456,
      71.456,
      68.977,
      68.977,
      68.845,
      68.845,
      68.276,
      68.276,
      51.135,
      51.135,
      82.329,
      82.329,
      36.805,
      36.805,
      79.2,
      79.2,
      56.126,
      56.126,
      69.612,
      69.612,
      69.09,
      69.09,
      70.447,
      70.447,
      74.266,
      74.266,
      78.097,
      78.097,
      72.008,
      72.008,
      83.928,
      83.928,
      66.788,
      66.788,
      90.635,
      90.635,
      65.213,
      65.213,
      90.658,
      90.658,
      80.628,
      80.628,
      65.283,
      65.283,
      70.548,
      70.548,
      74.201,
      74.201,
      91.015,
      91.015,
      61.73,
      61.73,
      81.478,
      81.478,
      82.196,
      82.196,
      82.38,
      82.38,
      102.003,
      102.003,
      78.965,
      78.965,
      110.438,
      110.438,
      95.36,
      95.36,
      92.676,
      92.676,
      95.243,
      95.243,
      91.444,
      91.444,
      90.786,
      90.786,
      84.643,
      84.643,
      72.157,
      72.157,
      103.841,
      103.841,
      88.268,
      88.268,
      79.16,
      79.16
    ],
    "primary": [
      10.181,
      10.181,
      9.245,
      9.245,
      11.925,
      11.925,
      7.925,
      7.925,
      9.533,
      9.533,
      10.051,
      10.051,
      11.422,
      11.422,
      12.329,
      12.329,
      8.28,
      8.28,
      11.014,
      11.014,
      11.284,
      11.284,
      8.429,
      8.429,
      10.616,
      10.616,
      10.252,
      10.252,
      9.272,
      9.272,
      11.144,
      11.144,
      13.272,
      13.272,
      11.231,
      11.231,
      11.958,
      11.958,
      10.757,
      10.757,
      8.959,
      8.959,
      11.861,
      11.861,
      9.881,
      9.881,
      11.613,
      11.613,
      13.061,
      13.061,
      10.035,
      10.035,
      11.245,
      11.245,
      11.219,
      11.219,
      8.044,
      8.044,
      11.191,
      11.191,
      12.675,
      12.675,
      7.554,
      7.554,
      11.407,
      11.407,
      11.554,
      11.554,
      11.684,
      11.684,
      3.674,
      3.674,
      7.336,
      7.336,
      0.416,
      0.416,
      3.24,
      3.24,
      5.028,
      5.028,
      2.003,
      2.003,
      2.696,
      2.696,
      1.371,
      1.371,
      7.962,
      7.962,
      5.799,
      5.799,
      0.1,
      0.1,
      4.857,
      4.857,
      9.679,
      9.679,
      10.181,
      10.181,
      9.245,
      9.245,
      11.925,
      11.925,
      7.925,
      7.925,
      9.533,
      9.533,
      10.051,
      10.051,
      11.422,
      11.422,
      12.329,
      12.329,
      8.28,
      8.28,
      11.014,
      11.014,
      11.284,
      11.284,
      8.429,
      8.429,
      10.616,
      10.616,
      10.252,
      10.252,
      9.272,
      9.272,
      11.144,
      11.144,
      13.272,
      13.272,
      11.231,
      11.231,
      11.958,
      11.958,
      10.757,
      10.757,
      8.959,
      8.959,
      11.861,
      11.861,
      9.881,
      9.881,
      11.613,
      11.613,
      13.061,
      13.061,
      10.035,
      10.035,
      11.245,
      11.245,
      11.219,
      11.219,
      8.044,
      8.044,
      11.191,
      11.191,
      12.675,
      12.675,
      7.554,
      7.554,
      11.407,
      11.407,
      11.554,
      11.554,
      11.684,
      11.684,
      3.674,
      3.674,
      7.336,
      7.336,
      0.416,
      0.416,
      3.24,
      3.24,
      5.028,
      5.028,
      2.003,
      2.003,
      2.696,
      2.696,
      1.371,
      1.371,
      7.962,
      7.962,
      5.799,
      5.799,
      0.1,
      0.1,
      4.857,
      4.857,
      9.679,
      9.679
    ],
    "secondary": [
      11.575,
      11.575,
      10.165,
      10.165,
      14.194,
      14.194,
      8.116,
      8.116,
      11.262,
      11.262,
      11.597,
      11.597,
      13.384,
      13.384,
      14.208,
      14.208,
      9.341,
      9.341,
      11.984,
      11.984,
      12.486,
      12.486,
      9.38,
      9.38,
      13.419,
      13.419,
      10.336,
      10.336,
      12.321,
      12.321,
      11.268,
      11.268,
      12.031,
      12.031,
      12.41,
      12.41,
      12.091,
      12.091,
      10.745,
      10.745,
      8.96,
      8.96,
      7.524,
      7.524,
      11.285,
      11.285,
      1.85,
      1.85,
      15.839,
      15.839,
      5.145,
      5.145,
      9.369,
      9.369,
      15.259,
      15.259,
      5.881,
      5.881,
      9.399,
      9.399,
      4.192,
      4.192,
      13.02,
      13.02,
      8.955,
      8.955,
      8.735,
      8.735,
      8.844,
      8.844,
      2.221,
      2.221,
      10.034,
      10.034,
      3.953,
      3.953,
      6.308,
      6.308,
      6.066,
      6.066,
      3.641,
      3.641,
      5.291,
      5.291,
      5.43,
      5.43,
      2.382,
      2.382,
      15.444,
      15.444,
      2.757,
      2.757,
      14.423,
      14.423,
      11.256,
      11.256,
      11.575,
      11.575,
      10.165,
      10.165,
      14.194,
      14.194,
      8.116,
      8.116,
      11.262,
      11.262,
      11.597,
      11.597,
      13.384,
      13.384,
      14.208,
      14.208,
      9.341,
      9.341,
      11.984,
      11.984,
      12.486,
      12.486,
      9.38,
      9.38,
      13.419,
      13.419,
      10.336,
      10.336,
      12.321,
      12.321,
      11.268,
      11.268,
      12.031,
      12.031,
      12.41,
      12.41,
      12.091,
      12.091,
      10.745,
      10.745,
      8.96,
      8.96,
      7.524,
      7.524,
      11.285,
      11.285,
      1.85,
      1.85,
      15.839,
      15.839,
      5.145,
      5.145,
      9.369,
      9.369,
      15.259,
      15.259,
      5.881,
      5.881,
      9.399,
      9.399,
      4.192,
      4.192,
      13.02,
      13.02,
      8.955,
      8.955,
      8.735,
      8.735,
      8.844,
      8.844,
      2.221,
      2.221,
      10.034,
      10.034,
      3.953,
      3.953,
      6.308,
      6.308,
      6.066,
      6.066,
      3.641,
      3.641,
      5.291,
      5.291,
      5.43,
      5.43,
      2.382,
      2.382,
      15.444,
      15.444,
      2.757,
      2.757,
      14.423,
      14.423,
      11.256,
      11.256
    ]
  }
}
